LICENSE
README.md
setup.py
rstconn/__init__.py
rstconn/rstconn.py
rstconn.egg-info/PKG-INFO
rstconn.egg-info/SOURCES.txt
rstconn.egg-info/dependency_links.txt
rstconn.egg-info/requires.txt
rstconn.egg-info/top_level.txt
rstconn/bin/rstconn