Metadata-Version: 2.1
Name: rstconn
Version: 0.3.1
Summary: A TCPKill utility written in python and scapy
Home-page: https://github.com/4Securitas/rstconn
Author: Giuseppe De Marco
Author-email: demarcog83@gmail.com
License: License :: OSI Approved :: European Union Public Licence 1.2 (EUPL 1.2)
Platform: UNKNOWN
Classifier: Development Status :: 5 - Production/Stable
Classifier: License :: OSI Approved :: European Union Public Licence 1.2 (EUPL 1.2)
Classifier: Programming Language :: Python :: 3
License-File: LICENSE
